dremio/__init__.py
dremio/dremio.py
dremiopy/__init__.py
dremiopy/dremio.py
dremiopy-0.0.2.data/scripts/dremio.py
dremiopy-0.0.2.dist-info/LICENSE
dremiopy-0.0.2.dist-info/METADATA
dremiopy-0.0.2.dist-info/WHEEL
dremiopy-0.0.2.dist-info/top_level.txt
dremiopy-0.0.2.dist-info/RECORD
